employee_benefit_plans/__init__.py
employee_benefit_plans/py.typed
employee_benefit_plans/demographic_data_analytic/__init__.py
employee_benefit_plans/demographic_data_analytic/analytic.py
employee_benefit_plans-0.1.0.dist-info/METADATA
employee_benefit_plans-0.1.0.dist-info/WHEEL
employee_benefit_plans-0.1.0.dist-info/RECORD
