Metadata-Version: 2.3
Name: employee-benefit-plans
Version: 0.1.0
Summary: Add your description here
Author-email: lunelson-deloitte <lunelson@deloitte.com>
Requires-Python: >=3.10
Requires-Dist: attrs>=24.2.0
Requires-Dist: pydantic>=2.9.2
